any_agent/__init__.py
any_agent/config.py
any_agent/logging.py
any_agent/py.typed
any_agent/callbacks/__init__.py
any_agent/callbacks/base.py
any_agent/callbacks/context.py
any_agent/callbacks/span_cost.py
any_agent/callbacks/span_end.py
any_agent/callbacks/span_print.py
any_agent/callbacks/span_generation/__init__.py
any_agent/callbacks/span_generation/agno.py
any_agent/callbacks/span_generation/base.py
any_agent/callbacks/span_generation/google.py
any_agent/callbacks/span_generation/langchain.py
any_agent/callbacks/span_generation/llama_index.py
any_agent/callbacks/span_generation/openai.py
any_agent/callbacks/span_generation/smolagents.py
any_agent/callbacks/span_generation/tinyagent.py
any_agent/callbacks/wrappers/__init__.py
any_agent/callbacks/wrappers/agno.py
any_agent/callbacks/wrappers/google.py
any_agent/callbacks/wrappers/langchain.py
any_agent/callbacks/wrappers/llama_index.py
any_agent/callbacks/wrappers/openai.py
any_agent/callbacks/wrappers/smolagents.py
any_agent/callbacks/wrappers/tinyagent.py
any_agent/evaluation/__init__.py
any_agent/evaluation/agent_judge.py
any_agent/evaluation/llm_judge.py
any_agent/evaluation/schemas.py
any_agent/evaluation/tools.py
any_agent/frameworks/__init__.py
any_agent/frameworks/agno.py
any_agent/frameworks/any_agent.py
any_agent/frameworks/google.py
any_agent/frameworks/langchain.py
any_agent/frameworks/llama_index.py
any_agent/frameworks/openai.py
any_agent/frameworks/smolagents.py
any_agent/frameworks/tinyagent.py
any_agent/serving/__init__.py
any_agent/serving/server_handle.py
any_agent/serving/a2a/__init__.py
any_agent/serving/a2a/agent_card.py
any_agent/serving/a2a/agent_executor.py
any_agent/serving/a2a/config_a2a.py
any_agent/serving/a2a/context_manager.py
any_agent/serving/a2a/envelope.py
any_agent/serving/a2a/server_a2a.py
any_agent/serving/mcp/__init__.py
any_agent/serving/mcp/config_mcp.py
any_agent/serving/mcp/server_mcp.py
any_agent/testing/__init__.py
any_agent/testing/helpers.py
realtimex_any_agent-0.1.0.dist-info/licenses/LICENSE
realtimex_any_agent-0.1.0.dist-info/METADATA
realtimex_any_agent-0.1.0.dist-info/WHEEL
realtimex_any_agent-0.1.0.dist-info/entry_points.txt
realtimex_any_agent-0.1.0.dist-info/top_level.txt
realtimex_any_agent-0.1.0.dist-info/RECORD
